spacebridge_mcp/__init__.py
spacebridge_mcp/duplicate_detection.py
spacebridge_mcp/resources.py
spacebridge_mcp/server.py
spacebridge_mcp/spacebridge_client.py
spacebridge_mcp/tools.py
spacebridge_mcp-0.3.0.dist-info/licenses/LICENSE
spacebridge_mcp-0.3.0.dist-info/METADATA
spacebridge_mcp-0.3.0.dist-info/WHEEL
spacebridge_mcp-0.3.0.dist-info/entry_points.txt
spacebridge_mcp-0.3.0.dist-info/top_level.txt
spacebridge_mcp-0.3.0.dist-info/RECORD
