Metadata-Version: 2.4
Name: spacebridge-mcp
Version: 0.3.0
Summary: SpaceBridge MCP Server for issue tracker automation.
Author-email: Spacecode AI Inc <hello@spacecode.ai>
License-Expression: MIT
Project-URL: Homepage, https://github.com/spacecode-ai/SpaceBridge-MCP
Project-URL: Bug Tracker, https://github.com/spacecode-ai/SpaceBridge-MCP/issues
Project-URL: Documentation, https://spacebridge.io/docs
Classifier: Programming Language :: Python :: 3
Classifier: Operating System :: OS Independent
Classifier: Topic :: Software Development :: Libraries :: Python Modules
Classifier: Topic :: Communications
Requires-Python: >=3.9
License-File: LICENSE
Requires-Dist: mcp[cli]>=1.6.0
Requires-Dist: requests>=2.20.0
Requires-Dist: openai>=1.0.0
Requires-Dist: python-dotenv>=0.19.0
Requires-Dist: packaging>=21.0
Provides-Extra: dev
Requires-Dist: pytest>=7.0.0; extra == "dev"
Requires-Dist: pytest-asyncio>=0.20.0; extra == "dev"
Requires-Dist: respx>=0.20.0; extra == "dev"
Requires-Dist: httpx>=0.23.0; extra == "dev"
Requires-Dist: pre-commit>=4.2.0; extra == "dev"
Requires-Dist: ruff>=0.11.3; extra == "dev"
Dynamic: license-file
